{
  "iterations": 100000,
  "comment": "LGD beat VP",
  "team_outcomes": {
    "INVICTUS GAMING": {
      "1st": 4383,
      "2nd": 6370,
      "3rd": 14667,
      "4th": 25617,
      "5-6th": 48963,
      "7-8th": 0,
      "9-12th": 0,
      "13-16th": 0,
      "17-18th": 0,
      "gr_a_wb": 100000,
      "gr_a_lb": 0,
      "gr_a_elim": 0
    },
    "Virtus.pro": {
      "1st": 6474,
      "2nd": 8033,
      "3rd": 16962,
      "4th": 27137,
      "5-6th": 41394,
      "7-8th": 0,
      "9-12th": 0,
      "13-16th": 0,
      "17-18th": 0,
      "gr_a_wb": 100000,
      "gr_a_lb": 0,
      "gr_a_elim": 0
    },
    "OG": {
      "1st": 1132,
      "2nd": 2300,
      "3rd": 5631,
      "4th": 11312,
      "5-6th": 29165,
      "7-8th": 50460,
      "9-12th": 0,
      "13-16th": 0,
      "17-18th": 0,
      "gr_a_wb": 100000,
      "gr_a_lb": 0,
      "gr_a_elim": 0
    },
    "T1": {
      "1st": 367,
      "2nd": 1064,
      "3rd": 3219,
      "4th": 7709,
      "5-6th": 20922,
      "7-8th": 66719,
      "9-12th": 0,
      "13-16th": 0,
      "17-18th": 0,
      "gr_a_wb": 100000,
      "gr_a_lb": 0,
      "gr_a_elim": 0
    },
    "Undying": {
      "1st": 0,
      "2nd": 0,
      "3rd": 0,
      "4th": 0,
      "5-6th": 0,
      "7-8th": 0,
      "9-12th": 0,
      "13-16th": 100000,
      "17-18th": 0,
      "gr_a_wb": 0,
      "gr_a_lb": 100000,
      "gr_a_elim": 0
    },
    "Evil Geniuses": {
      "1st": 0,
      "2nd": 0,
      "3rd": 0,
      "4th": 0,
      "5-6th": 0,
      "7-8th": 0,
      "9-12th": 100000,
      "13-16th": 0,
      "17-18th": 0,
      "gr_a_wb": 0,
      "gr_a_lb": 100000,
      "gr_a_elim": 0
    },
    "Team Aster": {
      "1st": 0,
      "2nd": 0,
      "3rd": 0,
      "4th": 0,
      "5-6th": 0,
      "7-8th": 0,
      "9-12th": 0,
      "13-16th": 100000,
      "17-18th": 0,
      "gr_a_wb": 0,
      "gr_a_lb": 100000,
      "gr_a_elim": 0
    },
    "Alliance": {
      "1st": 0,
      "2nd": 0,
      "3rd": 0,
      "4th": 0,
      "5-6th": 0,
      "7-8th": 0,
      "9-12th": 100000,
      "13-16th": 0,
      "17-18th": 0,
      "gr_a_wb": 0,
      "gr_a_lb": 100000,
      "gr_a_elim": 0
    },
    "Thunder Predator": {
      "1st": 0,
      "2nd": 0,
      "3rd": 0,
      "4th": 0,
      "5-6th": 0,
      "7-8th": 0,
      "9-12th": 0,
      "13-16th": 0,
      "17-18th": 100000,
      "gr_a_wb": 0,
      "gr_a_lb": 0,
      "gr_a_elim": 100000
    },
    "PSG.LGD": {
      "1st": 46288,
      "2nd": 34995,
      "3rd": 18717,
      "4th": 0,
      "5-6th": 0,
      "7-8th": 0,
      "9-12th": 0,
      "13-16th": 0,
      "17-18th": 0,
      "gr_b_wb": 100000,
      "gr_b_lb": 0,
      "gr_b_elim": 0
    },
    "Team Secret": {
      "1st": 35801,
      "2nd": 39741,
      "3rd": 24458,
      "4th": 0,
      "5-6th": 0,
      "7-8th": 0,
      "9-12th": 0,
      "13-16th": 0,
      "17-18th": 0,
      "gr_b_wb": 100000,
      "gr_b_lb": 0,
      "gr_b_elim": 0
    },
    "Vici Gaming": {
      "1st": 4305,
      "2nd": 5136,
      "3rd": 10456,
      "4th": 16707,
      "5-6th": 30115,
      "7-8th": 33281,
      "9-12th": 0,
      "13-16th": 0,
      "17-18th": 0,
      "gr_b_wb": 100000,
      "gr_b_lb": 0,
      "gr_b_elim": 0
    },
    "Team Spirit": {
      "1st": 1250,
      "2nd": 2361,
      "3rd": 5890,
      "4th": 11518,
      "5-6th": 29441,
      "7-8th": 49540,
      "9-12th": 0,
      "13-16th": 0,
      "17-18th": 0,
      "gr_b_wb": 100000,
      "gr_b_lb": 0,
      "gr_b_elim": 0
    },
    "beastcoast": {
      "1st": 0,
      "2nd": 0,
      "3rd": 0,
      "4th": 0,
      "5-6th": 0,
      "7-8th": 0,
      "9-12th": 0,
      "13-16th": 100000,
      "17-18th": 0,
      "gr_b_wb": 0,
      "gr_b_lb": 100000,
      "gr_b_elim": 0
    },
    "Quincy Crew": {
      "1st": 0,
      "2nd": 0,
      "3rd": 0,
      "4th": 0,
      "5-6th": 0,
      "7-8th": 0,
      "9-12th": 100000,
      "13-16th": 0,
      "17-18th": 0,
      "gr_b_wb": 0,
      "gr_b_lb": 100000,
      "gr_b_elim": 0
    },
    "Fnatic": {
      "1st": 0,
      "2nd": 0,
      "3rd": 0,
      "4th": 0,
      "5-6th": 0,
      "7-8th": 0,
      "9-12th": 100000,
      "13-16th": 0,
      "17-18th": 0,
      "gr_b_wb": 0,
      "gr_b_lb": 100000,
      "gr_b_elim": 0
    },
    "Elephant": {
      "1st": 0,
      "2nd": 0,
      "3rd": 0,
      "4th": 0,
      "5-6th": 0,
      "7-8th": 0,
      "9-12th": 0,
      "13-16th": 100000,
      "17-18th": 0,
      "gr_b_wb": 0,
      "gr_b_lb": 100000,
      "gr_b_elim": 0
    },
    "SG esports": {
      "1st": 0,
      "2nd": 0,
      "3rd": 0,
      "4th": 0,
      "5-6th": 0,
      "7-8th": 0,
      "9-12th": 0,
      "13-16th": 0,
      "17-18th": 100000,
      "gr_b_wb": 0,
      "gr_b_lb": 0,
      "gr_b_elim": 100000
    }
  },
  "updated": "14 October 2021 19:39:53"
}